formats/__init__.py
formats/api.py
formats/banks.py
formats/helpers.py
formats-0.1.1.dist-info/METADATA
formats-0.1.1.dist-info/DESCRIPTION.rst
formats-0.1.1.dist-info/top_level.txt
formats-0.1.1.dist-info/metadata.json
formats-0.1.1.dist-info/RECORD
formats-0.1.1.dist-info/WHEEL
