Metadata-Version: 1.1
Name: formats
Version: 0.1.1
Summary: Support multiple formats with ease
Home-page: https://github.com/redodo/formats
Author: Hidde Bultsma
Author-email: dodo@gododo.co
License: MIT
Keywords: formats,load,dump,parse,compose,convert
Platform: UNKNOWN
Classifier: Development Status :: 5 - Production/Stable
Classifier: Intended Audience :: Developers
Classifier: License :: OSI Approved :: MIT License
Classifier: Programming Language :: Python :: 2
Classifier: Programming Language :: Python :: 2.6
Classifier: Programming Language :: Python :: 2.7
Classifier: Programming Language :: Python :: 3
Classifier: Programming Language :: Python :: 3.2
Classifier: Programming Language :: Python :: 3.3
Classifier: Programming Language :: Python :: 3.4
